odoo/addons/edi_ediversa_oca_invoice_send/README.rst
odoo/addons/edi_ediversa_oca_invoice_send/__init__.py
odoo/addons/edi_ediversa_oca_invoice_send/__manifest__.py
odoo/addons/edi_ediversa_oca_invoice_send/components/__init__.py
odoo/addons/edi_ediversa_oca_invoice_send/components/account_move_edi_ediversa_listener.py
odoo/addons/edi_ediversa_oca_invoice_send/components/ediversa_generate_invoice.py
odoo/addons/edi_ediversa_oca_invoice_send/components/ediversa_send_invoice.py
odoo/addons/edi_ediversa_oca_invoice_send/data/edi.xml
odoo/addons/edi_ediversa_oca_invoice_send/i18n/edi_ediversa_oca_invoice_send.pot
odoo/addons/edi_ediversa_oca_invoice_send/i18n/it.po
odoo/addons/edi_ediversa_oca_invoice_send/models/__init__.py
odoo/addons/edi_ediversa_oca_invoice_send/models/account_move.py
odoo/addons/edi_ediversa_oca_invoice_send/models/account_move_line.py
odoo/addons/edi_ediversa_oca_invoice_send/models/account_tax.py
odoo/addons/edi_ediversa_oca_invoice_send/models/res_partner.py
odoo/addons/edi_ediversa_oca_invoice_send/readme/CONFIGURE.md
odoo/addons/edi_ediversa_oca_invoice_send/readme/CONTRIBUTORS.md
odoo/addons/edi_ediversa_oca_invoice_send/readme/DESCRIPTION.md
odoo/addons/edi_ediversa_oca_invoice_send/readme/USAGE.md
odoo/addons/edi_ediversa_oca_invoice_send/static/description/icon.png
odoo/addons/edi_ediversa_oca_invoice_send/static/description/index.html
odoo/addons/edi_ediversa_oca_invoice_send/tests/__init__.py
odoo/addons/edi_ediversa_oca_invoice_send/tests/test_edi_ediversa_invoice_send.py
odoo/addons/edi_ediversa_oca_invoice_send/views/account_tax_views.xml
odoo/addons/edi_ediversa_oca_invoice_send/views/res_partner_views.xml
odoo_addon_edi_ediversa_oca_invoice_send-17.0.1.0.1.dist-info/METADATA
odoo_addon_edi_ediversa_oca_invoice_send-17.0.1.0.1.dist-info/WHEEL
odoo_addon_edi_ediversa_oca_invoice_send-17.0.1.0.1.dist-info/top_level.txt
odoo_addon_edi_ediversa_oca_invoice_send-17.0.1.0.1.dist-info/RECORD
