Metadata-Version: 2.1
Name: odoo-addon-edi_ediversa_oca_invoice_send
Version: 17.0.1.0.1
Requires-Python: >=3.10
Requires-Dist: odoo-addon-edi_account_oca>=17.0dev,<17.1dev
Requires-Dist: odoo-addon-edi_ediversa_oca>=17.0dev,<17.1dev
Requires-Dist: odoo>=17.0a,<17.1dev
Summary: Send customer invoices to Ediversa
Home-page: https://github.com/OCA/edi-ediversa
License: AGPL-3
Author: Sygel, Odoo Community Association (OCA)
Author-email: support@odoo-community.org
Classifier: Programming Language :: Python
Classifier: Framework :: Odoo
Classifier: Framework :: Odoo :: 17.0
Classifier: License :: OSI Approved :: GNU Affero General Public License v3
